{
	"home_function_buttons": [
		{
			"id": "component_related",
			"info": {
				"zh-CN": {
					"title": "组件"
				},
				"en-UK": {
					"title": "Components"
				},
				"ar-SA": {
					"title": "مكونات"
				},
				"de-DE": {
					"title": "Komponenten"
				},
				"emoji": {
					"title": "🧩"
				},
				"es-ES": {
					"title": "Componentes"
				},
				"fr-FR": {
					"title": "Composants"
				},
				"hi-IN": {
					"title": "घटक"
				},
				"is-IS": {
					"title": "Íhlutir"
				},
				"it-IT": {
					"title": "Componenti"
				},
				"ja-JP": {
					"title": "コンポーネント"
				},
				"ko-KR": {
					"title": "컴포넌트"
				},
				"lzh": {
					"title": "組件"
				},
				"nl-NL": {
					"title": "Componenten"
				},
				"pt-PT": {
					"title": "Relacionado ao componente"
				},
				"ru-RU": {
					"title": "Компоненты"
				},
				"uk-UA": {
					"title": "Компонент"
				},
				"vi-VN": {
					"title": "Liên quan đến thành phần"
				},
				"zh-TW": {
					"title": "組件"
				}
			},
			"level": 1,
			"button": "<img src=\"https://api.iconify.design/mdi/puzzle-outline.svg\" class=\"text-icon\"/>",
			"sub_items": [
				{
					"info": {
						"zh-CN": {
							"title": "导出组件"
						},
						"en-UK": {
							"title": "Export Part"
						},
						"ar-SA": {
							"title": "مكونات التصدير"
						},
						"de-DE": {
							"title": "Part exportieren"
						},
						"emoji": {
							"title": "🧩📤"
						},
						"es-ES": {
							"title": "Exportar Parte"
						},
						"fr-FR": {
							"title": "Exporter Pièce"
						},
						"hi-IN": {
							"title": "पार्ट निर्यात करें"
						},
						"is-IS": {
							"title": "Útflutningshluta"
						},
						"it-IT": {
							"title": "Esporta Parte"
						},
						"ja-JP": {
							"title": "パートをエクスポート"
						},
						"ko-KR": {
							"title": "파트 내보내기"
						},
						"lzh": {
							"title": "導出器"
						},
						"nl-NL": {
							"title": "Exporteren componenten"
						},
						"pt-PT": {
							"title": "Exportar Parte"
						},
						"ru-RU": {
							"title": "Экспортировать часть"
						},
						"uk-UA": {
							"title": "Експортні компоненти"
						},
						"vi-VN": {
							"title": "Xuất bộ phận"
						},
						"zh-TW": {
							"title": "導出組件"
						}
					},
					"level": 2,
					"url": "/shells/export",
					"button": "<img src=\"https://api.iconify.design/line-md/folder-arrow-right.svg\" class=\"text-icon\"/>"
				}
			]
		}
	],
	"home_common_interfaces": [
		{
			"info": {
				"zh-CN": {
					"title": "导出"
				},
				"en-UK": {
					"title": "Export"
				},
				"ar-SA": {
					"title": "تصدير"
				},
				"de-DE": {
					"title": "Exportieren"
				},
				"emoji": {
					"title": "📤"
				},
				"es-ES": {
					"title": "Exportar"
				},
				"fr-FR": {
					"title": "Exporter"
				},
				"hi-IN": {
					"title": "निर्यात"
				},
				"is-IS": {
					"title": "Flytja út"
				},
				"it-IT": {
					"title": "Esporta"
				},
				"ja-JP": {
					"title": "エクスポート"
				},
				"ko-KR": {
					"title": "내보내기"
				},
				"lzh": {
					"title": "導出"
				},
				"nl-NL": {
					"title": "Exporteren"
				},
				"pt-PT": {
					"title": "Exportar"
				},
				"ru-RU": {
					"title": "Экспорт"
				},
				"uk-UA": {
					"title": "Експорт"
				},
				"vi-VN": {
					"title": "Xuất"
				},
				"zh-TW": {
					"title": "匯出"
				}
			},
			"level": 2,
			"url": "/shells/export?type=${type}&name=${name}",
			"button": "<img src=\"https://api.iconify.design/line-md/folder-arrow-right.svg\" class=\"text-icon\"/>"
		}
	],
	"home_drag_out_generators": [
		{
			"id": "generateDownloadUrl",
			"level": 0,
			"type": "DownloadURL",
			"path": "/shells/export/drag_generators/download_url.mjs",
			"info": {
				"zh-CN": {
					"description": "下载部件"
				},
				"en-UK": {
					"description": "Download part"
				},
				"ar-SA": {
					"description": "تنزيل الأجزاء"
				},
				"de-DE": {
					"description": "Teile herunterladen"
				},
				"emoji": {
					"description": "📥"
				},
				"es-ES": {
					"description": "Descargar piezas"
				},
				"fr-FR": {
					"description": "Télécharger des pièces"
				},
				"hi-IN": {
					"description": "भाग डाउनलोड करें"
				},
				"is-IS": {
					"description": "Sækja hluti"
				},
				"it-IT": {
					"description": "Scarica parti"
				},
				"ja-JP": {
					"description": "パーツをダウンロードする"
				},
				"ko-KR": {
					"description": "부품 다운로드"
				},
				"lzh": {
					"description": "載器"
				},
				"nl-NL": {
					"description": "Onderdelen downloaden"
				},
				"pt-PT": {
					"description": "Baixar peças"
				},
				"ru-RU": {
					"description": "Скачать части"
				},
				"uk-UA": {
					"description": "Завантажити частини"
				},
				"vi-VN": {
					"description": "Tải về các phần"
				},
				"zh-TW": {
					"description": "下載部件"
				}
			}
		}
	]
}
